shellfit.py
shellfitcli.py
shellfitfuncs.py
shellfit-2025.11.7.post3.dist-info/licenses/LICENSE
shellfit-2025.11.7.post3.dist-info/METADATA
shellfit-2025.11.7.post3.dist-info/WHEEL
shellfit-2025.11.7.post3.dist-info/entry_points.txt
shellfit-2025.11.7.post3.dist-info/top_level.txt
shellfit-2025.11.7.post3.dist-info/RECORD
