Metadata-Version: 2.4
Name: shellfit
Version: 2025.11.7.post3
Summary: A function fitting code utilizing shell-style history.
Author-email: Andrii Shyichuk <andrii.shyichuk@uwr.edu.pl>
License-Expression: CC-BY-NC-ND-4.0
Project-URL: Homepage, https://github.com/andrewshyichuk/shellfit
License-File: LICENSE
Requires-Dist: matplotlib
Requires-Dist: scipy
Requires-Dist: numpy
Dynamic: license-file
